AUTHORS
LICENSE
MANIFEST.in
README.md
setup.cfg
setup.py
py_ms_cognitive_ml/__init__.py
py_ms_cognitive_ml.egg-info/PKG-INFO
py_ms_cognitive_ml.egg-info/SOURCES.txt
py_ms_cognitive_ml.egg-info/dependency_links.txt
py_ms_cognitive_ml.egg-info/requires.txt
py_ms_cognitive_ml.egg-info/top_level.txt
py_ms_cognitive_ml/py_ms_cognitive_search/__init__.py
py_ms_cognitive_ml/py_ms_cognitive_search/py_ms_cognitive_image_search.py
py_ms_cognitive_ml/py_ms_cognitive_search/py_ms_cognitive_search.py