Metadata-Version: 1.2
Name: py-ms-cognitive-ml
Version: 0.0.2
Summary: Light wrapper for Microsoft's Cognitive Services API to facilitate data gathering for machine learning.
Home-page: https://github.com/beardo01/py-ms-cognitive-ml
Author: Oliver Reid
Author-email: reiol787@student.otago.ac.nz
License: MIT
Keywords: Microsoft,Cognitive Services,API,Search,Image Search,Machine Learning,Image Scraping
Platform: UNKNOWN
Classifier: Development Status :: 2 - Pre-Alpha
Classifier: Intended Audience :: Developers
Classifier: License :: OSI Approved :: MIT License
Classifier: Operating System :: OS Independent
Classifier: Programming Language :: Python :: 3
Classifier: Programming Language :: Python :: 3.2
Classifier: Programming Language :: Python :: 3.3
Classifier: Programming Language :: Python :: 3.4
Classifier: Topic :: Software Development :: Libraries :: Python Modules
Requires-Python: >=3
